sqs_pyio/__init__.py
sqs_pyio/boto3_client.py
sqs_pyio/io.py
sqs_pyio/options.py
sqs_pyio-0.1.0.dist-info/LICENSE
sqs_pyio-0.1.0.dist-info/METADATA
sqs_pyio-0.1.0.dist-info/WHEEL
sqs_pyio-0.1.0.dist-info/RECORD
