Metadata-Version: 2.1
Name: sqs_pyio
Version: 0.1.0
Summary: Apache Beam Python I/O connector for Amazon SQS
License: Apache-2.0
Author: Beam PyIO
Requires-Python: >=3.8,<3.13
Classifier: License :: OSI Approved :: Apache Software License
Classifier: Programming Language :: Python :: 3
Classifier: Programming Language :: Python :: 3.8
Classifier: Programming Language :: Python :: 3.9
Classifier: Programming Language :: Python :: 3.10
Classifier: Programming Language :: Python :: 3.11
Classifier: Programming Language :: Python :: 3.12
Requires-Dist: apache-beam[aws] (>=2.19.0)
Requires-Dist: certifi (>=2024.07.04)
Requires-Dist: numpy (==1.24.4) ; python_version == "3.8"
Requires-Dist: numpy (>1.24.4) ; python_version >= "3.9" and python_version < "3.13"
Requires-Dist: pandas (==2.0.3) ; python_version == "3.8"
Requires-Dist: pandas (>2.0.3) ; python_version >= "3.9" and python_version < "3.13"
Requires-Dist: scipy (==1.6.1) ; python_version == "3.8"
Requires-Dist: scipy (>1.6.1) ; python_version >= "3.9" and python_version < "3.13"
Requires-Dist: urllib3 (<2)
